{"output": 
[{"groupId": 1, "layer": ["Conv2d", "BatchNorm2d", "ReLU"], "nodeId": ["1", "2", "3"]}, 

{"groupId": 1, "layer": ["Conv2d", "BatchNorm2d", "ReLU"], "nodeId": ["4", "5", "6"]}, 

{"groupId": 0, "layer": "MaxPool2d", "nodeId": "7"}, 

{"groupId": 1, "layer": ["Conv2d", "BatchNorm2d", "ReLU"], "nodeId": ["8", "9", "10"]}, 

{"groupId": 1, "layer": ["Conv2d", "BatchNorm2d", "ReLU"], "nodeId": ["11", "12", "13"]}, 

{"groupId": 0, "layer": "MaxPool2d", "nodeId": "14"}, 

{"groupId": 1, "layer": ["Conv2d", "BatchNorm2d", "ReLU"], "nodeId": ["15", "16", "17"]}, 

{"groupId": 1, "layer": ["Conv2d", "BatchNorm2d", "ReLU"], "nodeId": ["18", "19", "20"]}, 

{"groupId": 1, "layer": ["Conv2d", "BatchNorm2d", "ReLU"], "nodeId": ["21", "22", "23"]}, 

{"groupId": 0, "layer": "MaxPool2d", "nodeId": "24"}, 

{"groupId": 1, "layer": ["Conv2d", "BatchNorm2d", "ReLU"], "nodeId": ["25", "26", "27"]}, 

{"groupId": 1, "layer": ["Conv2d", "BatchNorm2d", "ReLU"], "nodeId": ["28", "29", "30"]}, 

{"groupId": 1, "layer": ["Conv2d", "BatchNorm2d", "ReLU"], "nodeId": ["31", "32", "33"]}, 

{"groupId": 0, "layer": "MaxPool2d", "nodeId": "34"}, 

{"groupId": 1, "layer": ["Conv2d", "BatchNorm2d", "ReLU"], "nodeId": ["35", "36", "37"]}, 

{"groupId": 1, "layer": ["Conv2d", "BatchNorm2d", "ReLU"], "nodeId": ["38", "39", "40"]}, 

{"groupId": 1, "layer": ["Conv2d", "BatchNorm2d", "ReLU"], "nodeId": ["41", "42", "43"]}, 

{"groupId": 0, "layer": "MaxPool2d", "nodeId": "44"}, 

{"groupId": 0, "layer": "Linear", "nodeId": "45"},

{"groupId": 0, "layer": "ReLU", "nodeId": "46"}, 

{"groupId": 0, "layer": "Dropout", "nodeId": "47"}, 

{"groupId": 0, "layer": "Linear", "nodeId": "48"}, 

{"groupId": 0, "layer": "ReLU", "nodeId": "49"}, 

{"groupId": 0, "layer": "Dropout", "nodeId": "50"}, 

{"groupId": 0, "layer": "Linear", "nodeId": "51"}]}